{
 "cells": [
  {
   "cell_type": "code",
   "execution_count": 1,
   "id": "6cf53ea0-bea4-4983-8a1d-ee35d48f0bf6",
   "metadata": {},
   "outputs": [
    {
     "name": "stdout",
     "output_type": "stream",
     "text": [
      "Bytecode for square(x):\n",
      "  3           0 RESUME                   0\n",
      "\n",
      "  4           2 LOAD_FAST                0 (x)\n",
      "              4 LOAD_FAST                0 (x)\n",
      "              6 BINARY_OP                5 (*)\n",
      "             10 RETURN_VALUE\n",
      "\n",
      "\n",
      "Bytecode for add(a, b):\n",
      " 10           0 RESUME                   0\n",
      "\n",
      " 11           2 LOAD_FAST                0 (a)\n",
      "              4 LOAD_FAST                1 (b)\n",
      "              6 BINARY_OP                0 (+)\n",
      "             10 RETURN_VALUE\n",
      "\n",
      "\n",
      "Bytecode for multiply(a, b):\n",
      " 17           0 RESUME                   0\n",
      "\n",
      " 18           2 LOAD_FAST                0 (a)\n",
      "              4 LOAD_FAST                1 (b)\n",
      "              6 BINARY_OP                5 (*)\n",
      "             10 RETURN_VALUE\n"
     ]
    }
   ],
   "source": [
    "import dis\n",
    "\n",
    "def square(x):\n",
    "    return x * x\n",
    "    \n",
    "print(\"Bytecode for square(x):\")\n",
    "dis.dis(square)\n",
    "print(\"\\n\")\n",
    "\n",
    "def add(a, b):\n",
    "    return a + b\n",
    "\n",
    "print(\"Bytecode for add(a, b):\")\n",
    "dis.dis(add)\n",
    "print(\"\\n\")\n",
    "\n",
    "def multiply(a, b):\n",
    "    return a * b\n",
    "\n",
    "print(\"Bytecode for multiply(a, b):\")\n",
    "dis.dis(multiply)"
   ]
  },
  {
   "cell_type": "code",
   "execution_count": 2,
   "id": "4cc6d830-21a0-486e-9c27-616cf0e04c5e",
   "metadata": {},
   "outputs": [
    {
     "name": "stdout",
     "output_type": "stream",
     "text": [
      "Value: 12 Type: <class 'int'>\n",
      "Value: [1, 2, 3] Type: <class 'list'>\n",
      "Value: <function my_func at 0x0000027E26C3DD00> Type: <class 'function'>\n"
     ]
    }
   ],
   "source": [
    "data = 12\n",
    "print(\"Value:\", data, \"Type:\", type(data))\n",
    "\n",
    "data = [1, 2, 3]\n",
    "print(\"Value:\", data, \"Type:\", type(data))\n",
    "\n",
    "def my_func():\n",
    "    pass\n",
    "\n",
    "data = my_func\n",
    "print(\"Value:\", data, \"Type:\", type(data))"
   ]
  },
  {
   "cell_type": "code",
   "execution_count": 3,
   "id": "8b424aa0-d1e0-41ab-8fa4-e656c629a3da",
   "metadata": {},
   "outputs": [
    {
     "name": "stdout",
     "output_type": "stream",
     "text": [
      "Module(\n",
      "    body=[\n",
      "        Assign(\n",
      "            targets=[\n",
      "                Name(id='y', ctx=Store())],\n",
      "            value=BinOp(\n",
      "                left=BinOp(\n",
      "                    left=Constant(value=4),\n",
      "                    op=Mult(),\n",
      "                    right=Constant(value=5)),\n",
      "                op=Sub(),\n",
      "                right=Constant(value=3)))],\n",
      "    type_ignores=[])\n"
     ]
    }
   ],
   "source": [
    "import ast\n",
    "\n",
    "code = \"y = (4 * 5) - 3\"\n",
    "\n",
    "tree = ast.parse(code)\n",
    "\n",
    "print(ast.dump(tree, indent=4))"
   ]
  },
  {
   "cell_type": "code",
   "execution_count": 4,
   "id": "5d56edf9-3f83-434b-b8a1-2fbd6c77a401",
   "metadata": {},
   "outputs": [
    {
     "name": "stdout",
     "output_type": "stream",
     "text": [
      "Before append: [10, 20, 30] ID: 2740839686144\n",
      "After append: [10, 20, 30, 40] ID: 2740839686144\n"
     ]
    }
   ],
   "source": [
    "my_list = [10, 20, 30]\n",
    "\n",
    "print(\"Before append:\", my_list, \"ID:\", id(my_list))\n",
    "\n",
    "my_list.append(40)\n",
    "\n",
    "print(\"After append:\", my_list, \"ID:\", id(my_list))"
   ]
  }
 ],
 "metadata": {
  "kernelspec": {
   "display_name": "Python 3 (ipykernel)",
   "language": "python",
   "name": "python3"
  },
  "language_info": {
   "codemirror_mode": {
    "name": "ipython",
    "version": 3
   },
   "file_extension": ".py",
   "mimetype": "text/x-python",
   "name": "python",
   "nbconvert_exporter": "python",
   "pygments_lexer": "ipython3",
   "version": "3.11.3"
  }
 },
 "nbformat": 4,
 "nbformat_minor": 5
}
